logger_patch/__init__.py
logger_patch/logger_patch.py
crewai_logger_patch-0.1.dist-info/METADATA
crewai_logger_patch-0.1.dist-info/WHEEL
crewai_logger_patch-0.1.dist-info/top_level.txt
crewai_logger_patch-0.1.dist-info/RECORD
