Metadata-Version: 2.1
Name: crewai-logger_patch
Version: 0.1
Author: theCyberTech
Author-email: the_t3ch@pm.me
Requires-Dist: crewai
